bootkicker/__init__.py
bootkicker/main.py
bootkicker-0.1.1.dist-info/METADATA
bootkicker-0.1.1.dist-info/WHEEL
bootkicker-0.1.1.dist-info/entry_points.txt
bootkicker-0.1.1.dist-info/licenses/LICENSE
bootkicker-0.1.1.dist-info/RECORD
