Metadata-Version: 2.4
Name: bootkicker
Version: 0.1.1
Summary: CLI tool for AI-powered project specification review
Project-URL: Bug Reports, https://github.com/viet/bootkicker/issues
Project-URL: Source, https://github.com/viet/bootkicker
Author-email: Viet Nguyen <me@n12t.com>
License-Expression: MIT
License-File: LICENSE
Keywords: ai,cli,llm,openrouter,project,review,specification
Classifier: Development Status :: 4 - Beta
Classifier: Environment :: Console
Classifier: Intended Audience :: Developers
Classifier: License :: OSI Approved :: MIT License
Classifier: Operating System :: OS Independent
Classifier: Programming Language :: Python :: 3
Classifier: Programming Language :: Python :: 3.12
Classifier: Topic :: Scientific/Engineering :: Artificial Intelligence
Classifier: Topic :: Software Development :: Quality Assurance
Classifier: Topic :: Text Processing :: Markup :: Markdown
Requires-Python: >=3.12
Requires-Dist: aiohttp
Requires-Dist: langchain
Requires-Dist: openai
Requires-Dist: pyyaml
Requires-Dist: tqdm
